{
	"configurations" : 
	[
		{
			"directories" : 
			[
				{
					"build" : ".",
					"childIndexes" : 
					[
						1
					],
					"hasInstallRule" : true,
					"jsonFile" : "directory-.-Release-f5ebdc15457944623624.json",
					"minimumCMakeVersion" : 
					{
						"string" : "3.1"
					},
					"projectIndex" : 0,
					"source" : ".",
					"targetIndexes" : 
					[
						0,
						1,
						20,
						31,
						32
					]
				},
				{
					"build" : "ext",
					"childIndexes" : 
					[
						2,
						3,
						4,
						6
					],
					"hasInstallRule" : true,
					"jsonFile" : "directory-ext-Release-fa61a31e13d0f952d633.json",
					"minimumCMakeVersion" : 
					{
						"string" : "3.8"
					},
					"parentIndex" : 0,
					"projectIndex" : 0,
					"source" : "ext",
					"targetIndexes" : 
					[
						36
					]
				},
				{
					"build" : "ext/pugixml",
					"hasInstallRule" : true,
					"jsonFile" : "directory-ext.pugixml-Release-c23ef7ef1b70a42beca3.json",
					"minimumCMakeVersion" : 
					{
						"string" : "3.4"
					},
					"parentIndex" : 1,
					"projectIndex" : 1,
					"source" : "ext/pugixml",
					"targetIndexes" : 
					[
						2,
						3,
						4,
						5,
						6,
						7,
						8,
						9,
						10,
						11,
						12,
						13,
						14,
						15,
						16,
						17,
						18,
						19,
						21,
						22,
						23,
						24,
						25,
						26,
						27,
						28,
						29,
						30,
						37
					]
				},
				{
					"build" : "ext/glad",
					"jsonFile" : "directory-ext.glad-Release-d6d3884bb35bff9b90f5.json",
					"minimumCMakeVersion" : 
					{
						"string" : "3.1"
					},
					"parentIndex" : 1,
					"projectIndex" : 2,
					"source" : "ext/libigl/external/glad",
					"targetIndexes" : 
					[
						33
					]
				},
				{
					"build" : "ext/glfw",
					"childIndexes" : 
					[
						5
					],
					"jsonFile" : "directory-ext.glfw-Release-c4fb7155fd3f102ec8b4.json",
					"minimumCMakeVersion" : 
					{
						"string" : "3.1"
					},
					"parentIndex" : 1,
					"projectIndex" : 3,
					"source" : "ext/libigl/external/glfw"
				},
				{
					"build" : "ext/glfw/src",
					"jsonFile" : "directory-ext.glfw.src-Release-b877f4d40773aa2b8ce6.json",
					"minimumCMakeVersion" : 
					{
						"string" : "3.1"
					},
					"parentIndex" : 4,
					"projectIndex" : 3,
					"source" : "ext/libigl/external/glfw/src",
					"targetIndexes" : 
					[
						34
					]
				},
				{
					"build" : "ext/imgui",
					"jsonFile" : "directory-ext.imgui-Release-aeaae76713846edeb87c.json",
					"minimumCMakeVersion" : 
					{
						"string" : "3.1"
					},
					"parentIndex" : 1,
					"projectIndex" : 0,
					"source" : "ext/libigl/external/libigl-imgui",
					"targetIndexes" : 
					[
						35
					]
				}
			],
			"name" : "Release",
			"projects" : 
			[
				{
					"childIndexes" : 
					[
						1,
						2,
						3
					],
					"directoryIndexes" : 
					[
						0,
						1,
						6
					],
					"name" : "SpatialLinkages",
					"targetIndexes" : 
					[
						0,
						1,
						20,
						31,
						32,
						35,
						36
					]
				},
				{
					"directoryIndexes" : 
					[
						2
					],
					"name" : "pugixml",
					"parentIndex" : 0,
					"targetIndexes" : 
					[
						2,
						3,
						4,
						5,
						6,
						7,
						8,
						9,
						10,
						11,
						12,
						13,
						14,
						15,
						16,
						17,
						18,
						19,
						21,
						22,
						23,
						24,
						25,
						26,
						27,
						28,
						29,
						30,
						37
					]
				},
				{
					"directoryIndexes" : 
					[
						3
					],
					"name" : "glad",
					"parentIndex" : 0,
					"targetIndexes" : 
					[
						33
					]
				},
				{
					"directoryIndexes" : 
					[
						4,
						5
					],
					"name" : "GLFW",
					"parentIndex" : 0,
					"targetIndexes" : 
					[
						34
					]
				}
			],
			"targets" : 
			[
				{
					"directoryIndex" : 0,
					"id" : "3DCorelib::@6890427a1f51a3e7e1df",
					"jsonFile" : "target-3DCorelib-Release-8476c48e7f0bcbbaaf68.json",
					"name" : "3DCorelib",
					"projectIndex" : 0
				},
				{
					"directoryIndex" : 0,
					"id" : "3DRenderlib::@6890427a1f51a3e7e1df",
					"jsonFile" : "target-3DRenderlib-Release-39b19c7090ca6d3b6869.json",
					"name" : "3DRenderlib",
					"projectIndex" : 0
				},
				{
					"directoryIndex" : 2,
					"id" : "Continuous::@bfab0717ff4d40fb15cf",
					"jsonFile" : "target-Continuous-Release-9421538d311fa5b6576c.json",
					"name" : "Continuous",
					"projectIndex" : 1
				},
				{
					"directoryIndex" : 2,
					"id" : "ContinuousBuild::@bfab0717ff4d40fb15cf",
					"jsonFile" : "target-ContinuousBuild-Release-b56596d5a2008e3965f3.json",
					"name" : "ContinuousBuild",
					"projectIndex" : 1
				},
				{
					"directoryIndex" : 2,
					"id" : "ContinuousConfigure::@bfab0717ff4d40fb15cf",
					"jsonFile" : "target-ContinuousConfigure-Release-887f87f57914953067e2.json",
					"name" : "ContinuousConfigure",
					"projectIndex" : 1
				},
				{
					"directoryIndex" : 2,
					"id" : "ContinuousCoverage::@bfab0717ff4d40fb15cf",
					"jsonFile" : "target-ContinuousCoverage-Release-a74627c675ee1897749d.json",
					"name" : "ContinuousCoverage",
					"projectIndex" : 1
				},
				{
					"directoryIndex" : 2,
					"id" : "ContinuousMemCheck::@bfab0717ff4d40fb15cf",
					"jsonFile" : "target-ContinuousMemCheck-Release-940fcc681c33f6a909c6.json",
					"name" : "ContinuousMemCheck",
					"projectIndex" : 1
				},
				{
					"directoryIndex" : 2,
					"id" : "ContinuousStart::@bfab0717ff4d40fb15cf",
					"jsonFile" : "target-ContinuousStart-Release-7464c574eecb87693dd4.json",
					"name" : "ContinuousStart",
					"projectIndex" : 1
				},
				{
					"directoryIndex" : 2,
					"id" : "ContinuousSubmit::@bfab0717ff4d40fb15cf",
					"jsonFile" : "target-ContinuousSubmit-Release-93a3038483590d7f7fdb.json",
					"name" : "ContinuousSubmit",
					"projectIndex" : 1
				},
				{
					"directoryIndex" : 2,
					"id" : "ContinuousTest::@bfab0717ff4d40fb15cf",
					"jsonFile" : "target-ContinuousTest-Release-fa435fddb8e800facd65.json",
					"name" : "ContinuousTest",
					"projectIndex" : 1
				},
				{
					"directoryIndex" : 2,
					"id" : "ContinuousUpdate::@bfab0717ff4d40fb15cf",
					"jsonFile" : "target-ContinuousUpdate-Release-f74ee3c135516c093c92.json",
					"name" : "ContinuousUpdate",
					"projectIndex" : 1
				},
				{
					"directoryIndex" : 2,
					"id" : "Experimental::@bfab0717ff4d40fb15cf",
					"jsonFile" : "target-Experimental-Release-e9ec4b0549f36491e843.json",
					"name" : "Experimental",
					"projectIndex" : 1
				},
				{
					"directoryIndex" : 2,
					"id" : "ExperimentalBuild::@bfab0717ff4d40fb15cf",
					"jsonFile" : "target-ExperimentalBuild-Release-aa77cfc1340775f2d76d.json",
					"name" : "ExperimentalBuild",
					"projectIndex" : 1
				},
				{
					"directoryIndex" : 2,
					"id" : "ExperimentalConfigure::@bfab0717ff4d40fb15cf",
					"jsonFile" : "target-ExperimentalConfigure-Release-b64fa8027e14bbd71697.json",
					"name" : "ExperimentalConfigure",
					"projectIndex" : 1
				},
				{
					"directoryIndex" : 2,
					"id" : "ExperimentalCoverage::@bfab0717ff4d40fb15cf",
					"jsonFile" : "target-ExperimentalCoverage-Release-8c83bbfeec21074d91d2.json",
					"name" : "ExperimentalCoverage",
					"projectIndex" : 1
				},
				{
					"directoryIndex" : 2,
					"id" : "ExperimentalMemCheck::@bfab0717ff4d40fb15cf",
					"jsonFile" : "target-ExperimentalMemCheck-Release-939fdc162467f6e879cb.json",
					"name" : "ExperimentalMemCheck",
					"projectIndex" : 1
				},
				{
					"directoryIndex" : 2,
					"id" : "ExperimentalStart::@bfab0717ff4d40fb15cf",
					"jsonFile" : "target-ExperimentalStart-Release-77b907cd1de4ff7e808a.json",
					"name" : "ExperimentalStart",
					"projectIndex" : 1
				},
				{
					"directoryIndex" : 2,
					"id" : "ExperimentalSubmit::@bfab0717ff4d40fb15cf",
					"jsonFile" : "target-ExperimentalSubmit-Release-cff1ff2a7dfa63965c8c.json",
					"name" : "ExperimentalSubmit",
					"projectIndex" : 1
				},
				{
					"directoryIndex" : 2,
					"id" : "ExperimentalTest::@bfab0717ff4d40fb15cf",
					"jsonFile" : "target-ExperimentalTest-Release-d9b600b441ce254f5e6e.json",
					"name" : "ExperimentalTest",
					"projectIndex" : 1
				},
				{
					"directoryIndex" : 2,
					"id" : "ExperimentalUpdate::@bfab0717ff4d40fb15cf",
					"jsonFile" : "target-ExperimentalUpdate-Release-2356b4c0bf33cc8c503f.json",
					"name" : "ExperimentalUpdate",
					"projectIndex" : 1
				},
				{
					"directoryIndex" : 0,
					"id" : "Linkageslib::@6890427a1f51a3e7e1df",
					"jsonFile" : "target-Linkageslib-Release-fa9121e132f138389c59.json",
					"name" : "Linkageslib",
					"projectIndex" : 0
				},
				{
					"directoryIndex" : 2,
					"id" : "Nightly::@bfab0717ff4d40fb15cf",
					"jsonFile" : "target-Nightly-Release-a56635702f64d7d0ad53.json",
					"name" : "Nightly",
					"projectIndex" : 1
				},
				{
					"directoryIndex" : 2,
					"id" : "NightlyBuild::@bfab0717ff4d40fb15cf",
					"jsonFile" : "target-NightlyBuild-Release-c9756b057b4d0b68a4f7.json",
					"name" : "NightlyBuild",
					"projectIndex" : 1
				},
				{
					"directoryIndex" : 2,
					"id" : "NightlyConfigure::@bfab0717ff4d40fb15cf",
					"jsonFile" : "target-NightlyConfigure-Release-a1b7e1f2fc4293d8c170.json",
					"name" : "NightlyConfigure",
					"projectIndex" : 1
				},
				{
					"directoryIndex" : 2,
					"id" : "NightlyCoverage::@bfab0717ff4d40fb15cf",
					"jsonFile" : "target-NightlyCoverage-Release-03568695aabf2e8bc048.json",
					"name" : "NightlyCoverage",
					"projectIndex" : 1
				},
				{
					"directoryIndex" : 2,
					"id" : "NightlyMemCheck::@bfab0717ff4d40fb15cf",
					"jsonFile" : "target-NightlyMemCheck-Release-4057fcf312a8e739c269.json",
					"name" : "NightlyMemCheck",
					"projectIndex" : 1
				},
				{
					"directoryIndex" : 2,
					"id" : "NightlyMemoryCheck::@bfab0717ff4d40fb15cf",
					"jsonFile" : "target-NightlyMemoryCheck-Release-7c7b241fff87f06c9ea9.json",
					"name" : "NightlyMemoryCheck",
					"projectIndex" : 1
				},
				{
					"directoryIndex" : 2,
					"id" : "NightlyStart::@bfab0717ff4d40fb15cf",
					"jsonFile" : "target-NightlyStart-Release-53d83d143399641295a0.json",
					"name" : "NightlyStart",
					"projectIndex" : 1
				},
				{
					"directoryIndex" : 2,
					"id" : "NightlySubmit::@bfab0717ff4d40fb15cf",
					"jsonFile" : "target-NightlySubmit-Release-524bc5b85d9aa23fc769.json",
					"name" : "NightlySubmit",
					"projectIndex" : 1
				},
				{
					"directoryIndex" : 2,
					"id" : "NightlyTest::@bfab0717ff4d40fb15cf",
					"jsonFile" : "target-NightlyTest-Release-54deea8ffb9452bdd03d.json",
					"name" : "NightlyTest",
					"projectIndex" : 1
				},
				{
					"directoryIndex" : 2,
					"id" : "NightlyUpdate::@bfab0717ff4d40fb15cf",
					"jsonFile" : "target-NightlyUpdate-Release-20d21068ad3f4c5e321f.json",
					"name" : "NightlyUpdate",
					"projectIndex" : 1
				},
				{
					"directoryIndex" : 0,
					"id" : "Optlib::@6890427a1f51a3e7e1df",
					"jsonFile" : "target-Optlib-Release-ee3ce785eef3dcffb4fc.json",
					"name" : "Optlib",
					"projectIndex" : 0
				},
				{
					"directoryIndex" : 0,
					"id" : "SpatialLinkages_rMain::@6890427a1f51a3e7e1df",
					"jsonFile" : "target-SpatialLinkages_rMain-Release-7168716e2ddb205f9a55.json",
					"name" : "SpatialLinkages_rMain",
					"projectIndex" : 0
				},
				{
					"directoryIndex" : 3,
					"id" : "glad::@395c76cf0743a1c2a345",
					"jsonFile" : "target-glad-Release-d7f0335a028d71d0a114.json",
					"name" : "glad",
					"projectIndex" : 2
				},
				{
					"directoryIndex" : 5,
					"id" : "glfw::@f6f7721c76705297a9b5",
					"jsonFile" : "target-glfw-Release-56558de27a1c8c9b68cb.json",
					"name" : "glfw",
					"projectIndex" : 3
				},
				{
					"directoryIndex" : 6,
					"id" : "imgui::@b74f06831d21e0dfde8d",
					"jsonFile" : "target-imgui-Release-bd4f76bd9b290bfc3d65.json",
					"name" : "imgui",
					"projectIndex" : 0
				},
				{
					"directoryIndex" : 1,
					"id" : "imguizmo::@a9f99adfd9f636cea434",
					"jsonFile" : "target-imguizmo-Release-0bc569b4d3eecc40dde9.json",
					"name" : "imguizmo",
					"projectIndex" : 0
				},
				{
					"directoryIndex" : 2,
					"id" : "pugixml-shared::@bfab0717ff4d40fb15cf",
					"jsonFile" : "target-pugixml-shared-Release-6b24c9cfc3362201c298.json",
					"name" : "pugixml-shared",
					"projectIndex" : 1
				}
			]
		}
	],
	"kind" : "codemodel",
	"paths" : 
	{
		"build" : "/Users/yingjie/Documents/spatialLink_backup/cmake-build-release",
		"source" : "/Users/yingjie/Documents/spatialLink_backup"
	},
	"version" : 
	{
		"major" : 2,
		"minor" : 4
	}
}
